covid19br/__init__.py
covid19br/download.py
covid19br-0.0.2.dist-info/licenses/LICENSE
covid19br-0.0.2.dist-info/METADATA
covid19br-0.0.2.dist-info/WHEEL
covid19br-0.0.2.dist-info/top_level.txt
covid19br-0.0.2.dist-info/RECORD
