Metadata-Version: 2.4
Name: covid19br
Version: 0.0.2
Summary: Set of functions to import COVID-19 pandemic data into python
Author-email: "Fabio N. Demarqui" <fndemarqui@est.ufmg.br>
Project-URL: Homepage, https://github.com/fndemarqui/covid19br-py
Project-URL: Issues, https://github.com/fndemarqui/covid19br-py/issues
Classifier: Programming Language :: Python :: 3
Classifier: License :: OSI Approved :: MIT License
Classifier: Operating System :: OS Independent
Requires-Python: >=3.7
License-File: LICENSE
Requires-Dist: numpy
Requires-Dist: pandas
Requires-Dist: pyarrow
Requires-Dist: requests
Dynamic: license-file
